provenance_tools/__init__.py
provenance_tools/provenance_initializer.py
provenance_tools/provenance_tracker.py
provenance_tools/write_provenance_data.py
provenance_tools-0.0.5.dist-info/METADATA
provenance_tools-0.0.5.dist-info/WHEEL
provenance_tools-0.0.5.dist-info/entry_points.txt
provenance_tools-0.0.5.dist-info/top_level.txt
provenance_tools-0.0.5.dist-info/RECORD
