Metadata-Version: 2.1
Name: provenance-tools
Version: 0.0.5
Summary: provenance_tools
Home-page: https://github.com/acil-bwh/provenance_tools
Author: James Ross
Author-email: jross@bwh.harvard.edu
License: UNKNOWN
Platform: UNKNOWN
Classifier: Development Status :: 3 - Alpha
Classifier: Intended Audience :: Developers
Classifier: Topic :: Software Development :: Build Tools
Classifier: License :: OSI Approved :: MIT License
Classifier: Programming Language :: Python :: 3
Requires-Dist: gitpython
